label_studio_sdk/__init__.py
label_studio_sdk/_extensions/__init__.py
label_studio_sdk/_extensions/eval/categorical.py
label_studio_sdk/_extensions/label_studio_tools/__init__.py
label_studio_sdk/_extensions/label_studio_tools/core/__init__.py
label_studio_sdk/_extensions/label_studio_tools/core/label_config.py
label_studio_sdk/_extensions/label_studio_tools/core/utils/README.md
label_studio_sdk/_extensions/label_studio_tools/core/utils/__init__.py
label_studio_sdk/_extensions/label_studio_tools/core/utils/exceptions.py
label_studio_sdk/_extensions/label_studio_tools/core/utils/io.py
label_studio_sdk/_extensions/label_studio_tools/core/utils/json_schema.py
label_studio_sdk/_extensions/label_studio_tools/core/utils/params.py
label_studio_sdk/_extensions/label_studio_tools/etl/__init__.py
label_studio_sdk/_extensions/label_studio_tools/etl/beam.py
label_studio_sdk/_extensions/label_studio_tools/etl/example.py
label_studio_sdk/_extensions/label_studio_tools/etl/registry.py
label_studio_sdk/_extensions/label_studio_tools/postprocessing/__init__.py
label_studio_sdk/_extensions/label_studio_tools/postprocessing/video.py
label_studio_sdk/_extensions/pager_ext.py
label_studio_sdk/_legacy/__init__.py
label_studio_sdk/_legacy/client.py
label_studio_sdk/_legacy/exceptions.py
label_studio_sdk/_legacy/project.py
label_studio_sdk/_legacy/schema/label_config_schema.json
label_studio_sdk/_legacy/users.py
label_studio_sdk/_legacy/utils.py
label_studio_sdk/_legacy/workspaces.py
label_studio_sdk/actions/__init__.py
label_studio_sdk/actions/client.py
label_studio_sdk/actions/raw_client.py
label_studio_sdk/actions/types/__init__.py
label_studio_sdk/actions/types/create_actions_request_filters.py
label_studio_sdk/actions/types/create_actions_request_filters_conjunction.py
label_studio_sdk/actions/types/create_actions_request_filters_items_item.py
label_studio_sdk/actions/types/create_actions_request_filters_items_item_filter.py
label_studio_sdk-2.0.17.dist-info/LICENSE
label_studio_sdk-2.0.17.dist-info/METADATA
label_studio_sdk-2.0.17.dist-info/WHEEL
label_studio_sdk-2.0.17.dist-info/entry_points.txt
label_studio_sdk-2.0.17.dist-info/RECORD
