Metadata-Version: 2.3
Name: label-studio-sdk
Version: 2.0.17
Summary: 
Requires-Python: >=3.10,<4
Classifier: Intended Audience :: Developers
Classifier: Operating System :: MacOS
Classifier: Operating System :: Microsoft :: Windows
Classifier: Operating System :: OS Independent
Classifier: Operating System :: POSIX
Classifier: Operating System :: POSIX :: Linux
Classifier: Programming Language :: Python
Classifier: Programming Language :: Python :: 3
Classifier: Programming Language :: Python :: 3.10
Classifier: Programming Language :: Python :: 3.11
Classifier: Programming Language :: Python :: 3.12
Classifier: Programming Language :: Python :: 3.13
Classifier: Programming Language :: Python :: 3.8
Classifier: Programming Language :: Python :: 3.9
Classifier: Topic :: Software Development :: Libraries :: Python Modules
Classifier: Typing :: Typed
Requires-Dist: Pillow (>=11.3.0)
Requires-Dist: appdirs (>=1.4.3)
Requires-Dist: datamodel-code-generator (==0.26.1)
Requires-Dist: httpx (>=0.21.2)
Requires-Dist: ijson (>=3.2.3)
Requires-Dist: jsf (>=0.11.2,<0.12.0)
Requires-Dist: jsonschema (>=4.23.0)
Requires-Dist: lxml (>=4.2.5)
Requires-Dist: nltk (>=3.9.1,<4.0.0)
Requires-Dist: numpy (>=2.2,<3.0.0)
Requires-Dist: opencv-python-headless (>=4.12.0,<5.0.0)
Requires-Dist: pandas (>=0.24.0)
Requires-Dist: pydantic (>=1.9.2)
Requires-Dist: pydantic-core (>=2.18.2)
Requires-Dist: pyjwt (>=2.10.1,<3.0.0)
Requires-Dist: requests (>=2.22.0)
Requires-Dist: requests-mock (==1.12.1)
Requires-Dist: typing_extensions (>=4.0.0)
Requires-Dist: ujson (>=5.8.0)
Requires-Dist: urllib3 (>=2.5.0)
Requires-Dist: xmljson (==0.2.1)
Project-URL: Repository, https://github.com/HumanSignal/label-studio-sdk
